fyda/__init__.py
fyda/base.py
fyda/errorhandling.py
fyda/options.py
fyda-0.4.5.dist-info/LICENSE
fyda-0.4.5.dist-info/METADATA
fyda-0.4.5.dist-info/WHEEL
fyda-0.4.5.dist-info/top_level.txt
fyda-0.4.5.dist-info/RECORD
